{
  "accountAssociation": {
    "header": "",
    "payload": "",
    "signature": ""
  },
  "frame": {
    "version": "1",
    "name": "Resilience Rituals",
    "subtitle": "Built with Zara",
    "description": "Resilience Rituals is a Base Mini App built with Zara.",
    "iconUrl": "https://0co.to/images/zara-2.png",
    "homeUrl": "https://1afc9950-697b-4ac3-9ef5-e8d86e99eecf.vistara.dev",
    "splashImageUrl": "https://dummyimage.com/200x200/0a0b0d/ffffff.png&text=Splash",
    "splashBackgroundColor": "#000000",
    "heroImageUrl": "https://dummyimage.com/1200x628/0a0b0d/ffffff.png&text=Hero",
    "tagline": "Resilience Rituals",
    "screenshotUrls": [
      "https://dummyimage.com/1200x628/0a0b0d/ffffff.png&text=Shot1",
      "https://dummyimage.com/1200x628/0a0b0d/ffffff.png&text=Shot2"
    ],
    "primaryCategory": "social",
    "tags": [
      "base",
      "miniapp",
      "onchainkit"
    ],
    "webhookUrl": "https://1afc9950-697b-4ac3-9ef5-e8d86e99eecf.vistara.dev/api/webhook"
  }
}